tes_toolkit.py
tes_toolkit-1.1.1.dist-info/LICENSE
tes_toolkit-1.1.1.dist-info/METADATA
tes_toolkit-1.1.1.dist-info/WHEEL
tes_toolkit-1.1.1.dist-info/top_level.txt
tes_toolkit-1.1.1.dist-info/RECORD
