Metadata-Version: 2.1
Name: tes-toolkit
Version: 1.1.1
Summary: A toolkit for minmaxers of Elder Scrolls games
Author: Will Bolton
License: MIT License
Project-URL: repository, https://github.com/WillOnGit/tes-toolkit
Keywords: Elder Scrolls,Oblivion,Morrowind,Bethesda
Classifier: Development Status :: 5 - Production/Stable
Classifier: Environment :: Console
Classifier: Intended Audience :: End Users/Desktop
Classifier: License :: OSI Approved :: MIT License
Classifier: Natural Language :: English
Classifier: Programming Language :: Python :: 3
Classifier: Topic :: Games/Entertainment :: Role-Playing
Classifier: Topic :: Utilities
License-File: LICENSE
